{
  "Servers": {
    "1": {
      "Name": "ChiroERP - Finance DB",
      "Group": "ChiroERP",
      "Host": "postgres-finance",
      "Port": 5432,
      "MaintenanceDB": "postgres",
      "Username": "chiroerp",
      "SSLMode": "prefer"
    },
    "2": {
      "Name": "ChiroERP - Sales DB",
      "Group": "ChiroERP",
      "Host": "postgres-sales",
      "Port": 5432,
      "MaintenanceDB": "postgres",
      "Username": "chiroerp",
      "SSLMode": "prefer"
    },
    "3": {
      "Name": "ChiroERP - Inventory DB",
      "Group": "ChiroERP",
      "Host": "postgres-inventory",
      "Port": 5432,
      "MaintenanceDB": "postgres",
      "Username": "chiroerp",
      "SSLMode": "prefer"
    },
    "4": {
      "Name": "ChiroERP - Procurement DB",
      "Group": "ChiroERP",
      "Host": "postgres-procurement",
      "Port": 5432,
      "MaintenanceDB": "postgres",
      "Username": "chiroerp",
      "SSLMode": "prefer"
    },
    "5": {
      "Name": "ChiroERP - Production DB",
      "Group": "ChiroERP",
      "Host": "postgres-production",
      "Port": 5432,
      "MaintenanceDB": "postgres",
      "Username": "chiroerp",
      "SSLMode": "prefer"
    },
    "6": {
      "Name": "ChiroERP - Temporal DB",
      "Group": "ChiroERP",
      "Host": "postgres-temporal",
      "Port": 5432,
      "MaintenanceDB": "postgres",
      "Username": "temporal",
      "SSLMode": "prefer"
    }
  }
}
